{"1": {"pial_y": "51.2039", "pial_x": "20.0014", "pial_z": "0.192562", "dn_region": "cortical", "dn_fsname": "ctx-rh-lateralorbitofrontal", "dn_hemisphere": "right"}, "2": {"pial_y": "59.3178", "pial_x": "40.434", "pial_z": "6.99584", "dn_region": "cortical", "dn_fsname": "ctx-rh-parsorbitalis", "dn_hemisphere": "right"}, "3": {"pial_y": "86.1727", "pial_x": "5.77632", "pial_z": "5.35863", "dn_region": "cortical", "dn_fsname": "ctx-rh-frontalpole", "dn_hemisphere": "right"}, "4": {"pial_y": "59.1871", "pial_x": "3.14431", "pial_z": "2.09241", "dn_region": "cortical", "dn_fsname": "ctx-rh-medialorbitofrontal", "dn_hemisphere": "right"}, "5": {"pial_y": "47.0208", "pial_x": "42.4652", "pial_z": "21.4882", "dn_region": "cortical", "dn_fsname": "ctx-rh-parstriangularis", "dn_hemisphere": "right"}, "6": {"pial_y": "28.78", "pial_x": "44.3009", "pial_z": "32.8599", "dn_region": "cortical", "dn_fsname": "ctx-rh-parsopercularis", "dn_hemisphere": "right"}, "7": {"pial_y": "63.6589", "pial_x": "29.6793", "pial_z": "33.091", "dn_region": "cortical", "dn_fsname": "ctx-rh-rostralmiddlefrontal", "dn_hemisphere": "right"}, "8": {"pial_y": "42.8485", "pial_x": "10.7511", "pial_z": "57.3205", "dn_region": "cortical", "dn_fsname": "ctx-rh-superiorfrontal", "dn_hemisphere": "right"}, "9": {"pial_y": "29.3491", "pial_x": "34.1594", "pial_z": "57.5095", "dn_region": "cortical", "dn_fsname": "ctx-rh-caudalmiddlefrontal", "dn_hemisphere": "right"}, "10": {"pial_y": "1.54517", "pial_x": "32.9019", "pial_z": "58.6608", "dn_region": "cortical", "dn_fsname": "ctx-rh-precentral", "dn_hemisphere": "right"}, "11": {"pial_y": "-18.9683", "pial_x": "8.38124", "pial_z": "62.6225", "dn_region": "cortical", "dn_fsname": "ctx-rh-paracentral", "dn_hemisphere": "right"}, "12": {"pial_y": "51.6651", "pial_x": "2.2348", "pial_z": "17.9636", "dn_region": "cortical", "dn_fsname": "ctx-rh-rostralanteriorcingulate", "dn_hemisphere": "right"}, "13": {"pial_y": "35.9367", "pial_x": "3.72129", "pial_z": "42.5947", "dn_region": "cortical", "dn_fsname": "ctx-rh-caudalanteriorcingulate", "dn_hemisphere": "right"}, "14": {"pial_y": "-3.82833", "pial_x": "5.37663", "pial_z": "47.5258", "dn_region": "cortical", "dn_fsname": "ctx-rh-posteriorcingulate", "dn_hemisphere": "right"}, "15": {"pial_y": "-27.8213", "pial_x": "5.41446", "pial_z": "25.7851", "dn_region": "cortical", "dn_fsname": "ctx-rh-isthmuscingulate", "dn_hemisphere": "right"}, "16": {"pial_y": "-9.00963", "pial_x": "39.2214", "pial_z": "52.9724", "dn_region": "cortical", "dn_fsname": "ctx-rh-postcentral", "dn_hemisphere": "right"}, "17": {"pial_y": "-17.4688", "pial_x": "50.0866", "pial_z": "36.1604", "dn_region": "cortical", "dn_fsname": "ctx-rh-supramarginal", "dn_hemisphere": "right"}, "18": {"pial_y": "-49.4024", "pial_x": "25.1721", "pial_z": "49.4941", "dn_region": "cortical", "dn_fsname": "ctx-rh-superiorparietal", "dn_hemisphere": "right"}, "19": {"pial_y": "-46.65", "pial_x": "40.2184", "pial_z": "33.212", "dn_region": "cortical", "dn_fsname": "ctx-rh-inferiorparietal", "dn_hemisphere": "right"}, "20": {"pial_y": "-66.3139", "pial_x": "7.54952", "pial_z": "20.6866", "dn_region": "cortical", "dn_fsname": "ctx-rh-precuneus", "dn_hemisphere": "right"}, "21": {"pial_y": "-66.3139", "pial_x": "7.54952", "pial_z": "20.6866", "dn_region": "cortical", "dn_fsname": "ctx-rh-cuneus", "dn_hemisphere": "right"}, "22": {"pial_y": "-63.5787", "pial_x": "8.67992", "pial_z": "5.74737", "dn_region": "cortical", "dn_fsname": "ctx-rh-pericalcarine", "dn_hemisphere": "right"}, "23": {"pial_y": "-68.2919", "pial_x": "27.8516", "pial_z": "0.0323639", "dn_region": "cortical", "dn_fsname": "ctx-rh-lateraloccipital", "dn_hemisphere": "right"}, "24": {"pial_y": "-49.7002", "pial_x": "9.31479", "pial_z": "-2.52256", "dn_region": "cortical", "dn_fsname": "ctx-rh-lingual", "dn_hemisphere": "right"}, "25": {"pial_y": "-24.6329", "pial_x": "30.1626", "pial_z": "-12.6339", "dn_region": "cortical", "dn_fsname": "ctx-rh-fusiform", "dn_hemisphere": "right"}, "26": {"pial_y": "-9.89292", "pial_x": "20.0908", "pial_z": "-6.70407", "dn_region": "cortical", "dn_fsname": "ctx-rh-parahippocampal", "dn_hemisphere": "right"}, "27": {"pial_y": "17.7048", "pial_x": "17.1611", "pial_z": "-21.0119", "dn_region": "cortical", "dn_fsname": "ctx-rh-entorhinal", "dn_hemisphere": "right"}, "28": {"pial_y": "37.0293", "pial_x": "21.8148", "pial_z": "-16.3226", "dn_region": "cortical", "dn_fsname": "ctx-rh-temporalpole", "dn_hemisphere": "right"}, "29": {"pial_y": "-12.3872", "pial_x": "43.2313", "pial_z": "-13.3863", "dn_region": "cortical", "dn_fsname": "ctx-rh-inferiortemporal", "dn_hemisphere": "right"}, "30": {"pial_y": "-4.12753", "pial_x": "50.8025", "pial_z": "-4.22956", "dn_region": "cortical", "dn_fsname": "ctx-rh-middletemporal", "dn_hemisphere": "right"}, "31": {"pial_y": "-25.1783", "pial_x": "46.9803", "pial_z": "13.83", "dn_region": "cortical", "dn_fsname": "ctx-rh-bankssts", "dn_hemisphere": "right"}, "32": {"pial_y": "8.51425", "pial_x": "49.1986", "pial_z": "8.23651", "dn_region": "cortical", "dn_fsname": "ctx-rh-superiortemporal", "dn_hemisphere": "right"}, "33": {"pial_y": "-2.09941", "pial_x": "39.2795", "pial_z": "20.854", "dn_region": "cortical", "dn_fsname": "ctx-rh-transversetemporal", "dn_hemisphere": "right"}, "34": {"pial_y": "17.6497", "pial_x": "32.3818", "pial_z": "15.0344", "dn_region": "cortical", "dn_fsname": "ctx-rh-insula", "dn_hemisphere": "right"}, "35": {"pial_y": "-6.43246", "pial_x": "-0.176366", "pial_z": "25.4457", "dn_region": "subcortical", "dn_fsname": "Right-Thalamus-Proper", "dn_hemisphere": "right"}, "36": {"pial_y": "-6.43246", "pial_x": "-0.176366", "pial_z": "25.4457", "dn_region": "subcortical", "dn_fsname": "Right-Caudate", "dn_hemisphere": "right"}, "37": {"pial_y": "-6.43246", "pial_x": "-0.176366", "pial_z": "25.4457", "dn_region": "subcortical", "dn_fsname": "Right-Putamen", "dn_hemisphere": "right"}, "38": {"pial_y": "-6.43246", "pial_x": "-0.176366", "pial_z": "25.4457", "dn_region": "subcortical", "dn_fsname": "Right-Pallidum", "dn_hemisphere": "right"}, "39": {"pial_y": "-6.43246", "pial_x": "-0.176366", "pial_z": "25.4457", "dn_region": "subcortical", "dn_fsname": "Right-Accumbens-area", "dn_hemisphere": "right"}, "40": {"pial_y": "-6.43246", "pial_x": "-0.176366", "pial_z": "25.4457", "dn_region": "subcortical", "dn_fsname": "Right-Hippocampus", "dn_hemisphere": "right"}, "41": {"pial_y": "-6.43246", "pial_x": "-0.176366", "pial_z": "25.4457", "dn_region": "subcortical", "dn_fsname": "Right-Amygdala", "dn_hemisphere": "right"}, "42": {"pial_y": "50.8455", "pial_x": "-22.6184", "pial_z": "-0.803573", "dn_region": "cortical", "dn_fsname": "ctx-lh-lateralorbitofrontal", "dn_hemisphere": "left"}, "43": {"pial_y": "57.2185", "pial_x": "-40.0618", "pial_z": "4.54573", "dn_region": "cortical", "dn_fsname": "ctx-lh-parsorbitalis", "dn_hemisphere": "left"}, "44": {"pial_y": "85.629", "pial_x": "-8.42699", "pial_z": "10.9006", "dn_region": "cortical", "dn_fsname": "ctx-lh-frontalpole", "dn_hemisphere": "left"}, "45": {"pial_y": "61.8574", "pial_x": "-5.91568", "pial_z": "2.99213", "dn_region": "cortical", "dn_fsname": "ctx-lh-medialorbitofrontal", "dn_hemisphere": "left"}, "46": {"pial_y": "47.959", "pial_x": "-41.7179", "pial_z": "19.2551", "dn_region": "cortical", "dn_fsname": "ctx-lh-parstriangularis", "dn_hemisphere": "left"}, "47": {"pial_y": "29.4033", "pial_x": "-43.1451", "pial_z": "27.7255", "dn_region": "cortical", "dn_fsname": "ctx-lh-parsopercularis", "dn_hemisphere": "left"}, "48": {"pial_y": "58.478", "pial_x": "-31.4016", "pial_z": "34.4679", "dn_region": "cortical", "dn_fsname": "ctx-lh-rostralmiddlefrontal", "dn_hemisphere": "left"}, "49": {"pial_y": "34.7984", "pial_x": "-10.8772", "pial_z": "59.0169", "dn_region": "cortical", "dn_fsname": "ctx-lh-superiorfrontal", "dn_hemisphere": "left"}, "50": {"pial_y": "16.6186", "pial_x": "-30.0457", "pial_z": "60.6785", "dn_region": "cortical", "dn_fsname": "ctx-lh-caudalmiddlefrontal", "dn_hemisphere": "left"}, "51": {"pial_y": "-2.09195", "pial_x": "-35.7585", "pial_z": "53.9987", "dn_region": "cortical", "dn_fsname": "ctx-lh-precentral", "dn_hemisphere": "left"}, "52": {"pial_y": "-26.0851", "pial_x": "-7.44054", "pial_z": "60.3302", "dn_region": "cortical", "dn_fsname": "ctx-lh-paracentral", "dn_hemisphere": "left"}, "53": {"pial_y": "56.9759", "pial_x": "-4.1173", "pial_z": "18.4645", "dn_region": "cortical", "dn_fsname": "ctx-lh-rostralanteriorcingulate", "dn_hemisphere": "left"}, "54": {"pial_y": "37.743", "pial_x": "-4.8397", "pial_z": "42.6708", "dn_region": "cortical", "dn_fsname": "ctx-lh-caudalanteriorcingulate", "dn_hemisphere": "left"}, "55": {"pial_y": "-11.0923", "pial_x": "-6.23143", "pial_z": "45.9654", "dn_region": "cortical", "dn_fsname": "ctx-lh-posteriorcingulate", "dn_hemisphere": "left"}, "56": {"pial_y": "-27.6884", "pial_x": "-7.57098", "pial_z": "21.1128", "dn_region": "cortical", "dn_fsname": "ctx-lh-isthmuscingulate", "dn_hemisphere": "left"}, "57": {"pial_y": "-13.2789", "pial_x": "-43.1332", "pial_z": "50.8458", "dn_region": "cortical", "dn_fsname": "ctx-lh-postcentral", "dn_hemisphere": "left"}, "58": {"pial_y": "-25.4842", "pial_x": "-49.6934", "pial_z": "37.5988", "dn_region": "cortical", "dn_fsname": "ctx-lh-supramarginal", "dn_hemisphere": "left"}, "59": {"pial_y": "-54.2862", "pial_x": "-22.068", "pial_z": "47.7848", "dn_region": "cortical", "dn_fsname": "ctx-lh-superiorparietal", "dn_hemisphere": "left"}, "60": {"pial_y": "-57.867", "pial_x": "-35.2588", "pial_z": "29.9297", "dn_region": "cortical", "dn_fsname": "ctx-lh-inferiorparietal", "dn_hemisphere": "left"}, "61": {"pial_y": "-69.9361", "pial_x": "-4.74141", "pial_z": "18.5122", "dn_region": "cortical", "dn_fsname": "ctx-lh-precuneus", "dn_hemisphere": "left"}, "62": {"pial_y": "-69.9361", "pial_x": "-4.74141", "pial_z": "18.5122", "dn_region": "cortical", "dn_fsname": "ctx-lh-cuneus", "dn_hemisphere": "left"}, "63": {"pial_y": "-64.5092", "pial_x": "-6.31877", "pial_z": "6.70287", "dn_region": "cortical", "dn_fsname": "ctx-lh-pericalcarine", "dn_hemisphere": "left"}, "64": {"pial_y": "-73.948", "pial_x": "-22.4938", "pial_z": "-4.66033", "dn_region": "cortical", "dn_fsname": "ctx-lh-lateraloccipital", "dn_hemisphere": "left"}, "65": {"pial_y": "-52.4", "pial_x": "-11.4208", "pial_z": "-4.08995", "dn_region": "cortical", "dn_fsname": "ctx-lh-lingual", "dn_hemisphere": "left"}, "66": {"pial_y": "-27.3923", "pial_x": "-33.537", "pial_z": "-12.9608", "dn_region": "cortical", "dn_fsname": "ctx-lh-fusiform", "dn_hemisphere": "left"}, "67": {"pial_y": "-10.3271", "pial_x": "-24.1513", "pial_z": "-4.02292", "dn_region": "cortical", "dn_fsname": "ctx-lh-parahippocampal", "dn_hemisphere": "left"}, "68": {"pial_y": "12.0958", "pial_x": "-24.447", "pial_z": "-20.1142", "dn_region": "cortical", "dn_fsname": "ctx-lh-entorhinal", "dn_hemisphere": "left"}, "69": {"pial_y": "36.055", "pial_x": "-29.6371", "pial_z": "-18.8206", "dn_region": "cortical", "dn_fsname": "ctx-lh-temporalpole", "dn_hemisphere": "left"}, "70": {"pial_y": "-15.4713", "pial_x": "-46.3733", "pial_z": "-12.2849", "dn_region": "cortical", "dn_fsname": "ctx-lh-inferiortemporal", "dn_hemisphere": "left"}, "71": {"pial_y": "-10.7163", "pial_x": "-53.9447", "pial_z": "-1.57527", "dn_region": "cortical", "dn_fsname": "ctx-lh-middletemporal", "dn_hemisphere": "left"}, "72": {"pial_y": "-33.8167", "pial_x": "-50.2132", "pial_z": "14.5967", "dn_region": "cortical", "dn_fsname": "ctx-lh-bankssts", "dn_hemisphere": "left"}, "73": {"pial_y": "1.97222", "pial_x": "-49.3283", "pial_z": "9.39016", "dn_region": "cortical", "dn_fsname": "ctx-lh-superiortemporal", "dn_hemisphere": "left"}, "74": {"pial_y": "-8.31671", "pial_x": "-37.6637", "pial_z": "19.3382", "dn_region": "cortical", "dn_fsname": "ctx-lh-transversetemporal", "dn_hemisphere": "left"}, "75": {"pial_y": "15.0934", "pial_x": "-29.6954", "pial_z": "12.9627", "dn_region": "cortical", "dn_fsname": "ctx-lh-insula", "dn_hemisphere": "left"}, "76": {"pial_y": "-6.43246", "pial_x": "-0.176366", "pial_z": "25.4457", "dn_region": "subcortical", "dn_fsname": "Left-Thalamus-Proper", "dn_hemisphere": "left"}, "77": {"pial_y": "-6.43246", "pial_x": "-0.176366", "pial_z": "25.4457", "dn_region": "subcortical", "dn_fsname": "Left-Caudate", "dn_hemisphere": "left"}, "78": {"pial_y": "-6.43246", "pial_x": "-0.176366", "pial_z": "25.4457", "dn_region": "subcortical", "dn_fsname": "Left-Putamen", "dn_hemisphere": "left"}, "79": {"pial_y": "-6.43246", "pial_x": "-0.176366", "pial_z": "25.4457", "dn_region": "subcortical", "dn_fsname": "Left-Pallidum", "dn_hemisphere": "left"}, "80": {"pial_y": "-6.43246", "pial_x": "-0.176366", "pial_z": "25.4457", "dn_region": "subcortical", "dn_fsname": "Left-Accumbens-area", "dn_hemisphere": "left"}, "81": {"pial_y": "-6.43246", "pial_x": "-0.176366", "pial_z": "25.4457", "dn_region": "subcortical", "dn_fsname": "Left-Hippocampus", "dn_hemisphere": "left"}, "82": {"pial_y": "-6.43246", "pial_x": "-0.176366", "pial_z": "25.4457", "dn_region": "subcortical", "dn_fsname": "Left-Amygdala", "dn_hemisphere": "left"}, "83": {"pial_y": "-6.43246", "pial_x": "-0.176366", "pial_z": "25.4457", "dn_region": "subcortical", "dn_fsname": "Brain-Stem", "dn_hemisphere": "none"}}